axion/__init__.abi3.so
axion/executor.abi3.so
axion/factory.abi3.so
axion/pipeline.abi3.so
axion/queues.abi3.so
axion/recorder.abi3.so
axion/scheduler.abi3.so
axion/service.abi3.so
axion/thread.abi3.so
axion/bases/__init__.abi3.so
axion/bases/dbase.abi3.so
axion/bases/ibase.abi3.so
axion/bases/nbase.abi3.so
axion/bases/sbase.abi3.so
axion/bases/tbase.abi3.so
axion/bases/utility.abi3.so
axion-4.5.7.dist-info/licenses/project/LICENSE
axion-4.5.7.dist-info/METADATA
axion-4.5.7.dist-info/WHEEL
axion-4.5.7.dist-info/top_level.txt
axion-4.5.7.dist-info/RECORD
