Metadata-Version: 2.4
Name: axion
Version: 4.5.7
Summary: project description
Author-email: YL <fengyulong@pku.org.cn>
License-Expression: MIT
Project-URL: homepage, https://gitee.com
Project-URL: documentation, https://gitee.com
Project-URL: bugs, https://gitee.com
Classifier: Development Status :: 5 - Production/Stable
Classifier: Intended Audience :: Developers
Classifier: Intended Audience :: Science/Research
Classifier: Natural Language :: Chinese (Simplified)
Classifier: Natural Language :: English
Classifier: Operating System :: Microsoft :: Windows
Classifier: Operating System :: POSIX :: Linux
Classifier: Operating System :: MacOS :: MacOS X
Classifier: Programming Language :: Python :: 3.12
Classifier: Topic :: Scientific/Engineering :: Physics
Requires-Python: >=3.12
License-File: project/LICENSE
Requires-Dist: numpy>=1.20.0
Requires-Dist: h5py>=3.0.0
Requires-Dist: psutil>=5.8.0
Requires-Dist: srpc>=4.2.8
Requires-Dist: zee>=0.0.3
Dynamic: license-file
